hypebot/__init__.py
hypebot/log.py
hypebot/main.py
hypebot/net.py
hypebot/settings.py
hypebot/twitter.py
tests/__init__.py
tests/test_main.py
hypebot-0.1.0.dist-info/LICENSE
hypebot-0.1.0.dist-info/METADATA
hypebot-0.1.0.dist-info/WHEEL
hypebot-0.1.0.dist-info/entry_points.txt
hypebot-0.1.0.dist-info/top_level.txt
hypebot-0.1.0.dist-info/zip-safe
hypebot-0.1.0.dist-info/RECORD
