Metadata-Version: 2.1
Name: hypebot
Version: 0.1.0
Summary: Prepare for a whole bucket of hype from those that know humans best: computers
Home-page: UNKNOWN
Author: Jon Robison
Author-email: narfman0@gmail.com
License: LICENSE
Keywords: hypebot
Platform: UNKNOWN
Classifier: Development Status :: 4 - Beta
Classifier: License :: OSI Approved :: GNU General Public License v3 (GPLv3)
Classifier: Operating System :: OS Independent
Classifier: Programming Language :: Python
Classifier: Topic :: Software Development :: Libraries :: Python Modules
Requires-Dist: python-twitter
